sword_to_json/__init__.py
sword_to_json/__main__.py
sword_to_json/books_from_sword.py
sword_to_json/utils/__init__.py
sword_to_json/utils/metadata.py
sword_to_json/utils/progress.py
sword_to_json-4.1.0.dist-info/COPYING
sword_to_json-4.1.0.dist-info/METADATA
sword_to_json-4.1.0.dist-info/WHEEL
sword_to_json-4.1.0.dist-info/entry_points.txt
sword_to_json-4.1.0.dist-info/RECORD
