Metadata-Version: 2.1
Name: sword-to-json
Version: 4.1.0
Summary: Generate JSON Files of Bible Translations from SWORD Modules
Home-page: https://github.com/evnskc/sword-to-json
License: GPL-3.0-or-later
Keywords: sword,bible text,json
Author: Evans
Author-email: evans@fundi.dev
Requires-Python: >=3.11,<4.0
Classifier: License :: OSI Approved :: GNU General Public License v3 or later (GPLv3+)
Classifier: Programming Language :: Python :: 3
Classifier: Programming Language :: Python :: 3.11
Requires-Dist: pysword (>=0.2.8,<0.3.0)
Project-URL: Documentation, https://github.com/evnskc/sword-to-json
Project-URL: Repository, https://github.com/evnskc/sword-to-json
